{
	"configurations" : 
	[
		{
			"directories" : 
			[
				{
					"build" : ".",
					"childIndexes" : 
					[
						1,
						2,
						3,
						4
					],
					"jsonFile" : "directory-.-Debug-d0094a50bb2071803777.json",
					"minimumCMakeVersion" : 
					{
						"string" : "3.7"
					},
					"projectIndex" : 0,
					"source" : "."
				},
				{
					"build" : "src",
					"jsonFile" : "directory-src-Debug-c94b7c2814d5a21df52c.json",
					"minimumCMakeVersion" : 
					{
						"string" : "3.7"
					},
					"parentIndex" : 0,
					"projectIndex" : 0,
					"source" : "src",
					"targetIndexes" : 
					[
						0
					]
				},
				{
					"build" : "samples",
					"jsonFile" : "directory-samples-Debug-026e8de27727d40e5852.json",
					"minimumCMakeVersion" : 
					{
						"string" : "3.7"
					},
					"parentIndex" : 0,
					"projectIndex" : 0,
					"source" : "samples"
				},
				{
					"build" : "gtest",
					"jsonFile" : "directory-gtest-Debug-2618f1bde6c55d7920ba.json",
					"minimumCMakeVersion" : 
					{
						"string" : "3.7"
					},
					"parentIndex" : 0,
					"projectIndex" : 0,
					"source" : "gtest",
					"targetIndexes" : 
					[
						1
					]
				},
				{
					"build" : "tests",
					"jsonFile" : "directory-tests-Debug-70e4927a02b591d5c1f8.json",
					"minimumCMakeVersion" : 
					{
						"string" : "3.7"
					},
					"parentIndex" : 0,
					"projectIndex" : 0,
					"source" : "tests",
					"targetIndexes" : 
					[
						2
					]
				}
			],
			"name" : "Debug",
			"projects" : 
			[
				{
					"directoryIndexes" : 
					[
						0,
						1,
						2,
						3,
						4
					],
					"name" : "Lab_Stack",
					"targetIndexes" : 
					[
						0,
						1,
						2
					]
				}
			],
			"targets" : 
			[
				{
					"directoryIndex" : 1,
					"id" : "Lab_Stack::@145eef247bfb46b6828c",
					"jsonFile" : "target-Lab_Stack-Debug-e33cd9e6dee340409892.json",
					"name" : "Lab_Stack",
					"projectIndex" : 0
				},
				{
					"directoryIndex" : 3,
					"id" : "gtest::@0af4add9fe94340e763e",
					"jsonFile" : "target-gtest-Debug-726f877d74cd49e6c6a5.json",
					"name" : "gtest",
					"projectIndex" : 0
				},
				{
					"directoryIndex" : 4,
					"id" : "tests_Lab_Stack::@a44f0ac069e85531cdee",
					"jsonFile" : "target-tests_Lab_Stack-Debug-2788ce8f853fb94cdc71.json",
					"name" : "tests_Lab_Stack",
					"projectIndex" : 0
				}
			]
		}
	],
	"kind" : "codemodel",
	"paths" : 
	{
		"build" : "D:/Lab_Stack/Lab_Stack/out/build/x64-Debug",
		"source" : "D:/Lab_Stack/Lab_Stack"
	},
	"version" : 
	{
		"major" : 2,
		"minor" : 5
	}
}
